sensory_transcription/client/__init__.py
sensory_transcription/client/cli.py
sensory_transcription/client/config.py
sensory_transcription/client/core/__init__.py
sensory_transcription/client/core/async_client.py
sensory_transcription/client/core/chunker.py
sensory_transcription/client/core/io_utils.py
sensory_transcription/client/core/streaming_client.py
sensory_transcription/client/core/sync_client.py
sensory_transcription/models/__init__.py
sensory_transcription/server/__init__.py
sensory_transcription/server/config.py
sensory_transcription/server/main.py
sensory_transcription/server/api/dependencies.py
sensory_transcription/server/api/v1/batch.py
sensory_transcription/server/api/v1/stream.py
sensory_transcription/server/core/audio/preprocessor.py
sensory_transcription/server/core/services/__init__.py
sensory_transcription/server/core/services/advanced_processor.py
sensory_transcription/server/core/services/diarization_service.py
sensory_transcription/server/core/services/emo_service.py
sensory_transcription/server/core/services/stt_service.py
sensory_transcription/server/core/services/whisper_online.py
sensory_transcription/server/core/utils/converter.py
sensory_transcription/server/infra/cache/detector_interface.py
sensory_transcription/server/infra/cache/model_cache.py
sensory_transcription/server/infra/loaders/loader_factories.py
sensory_transcription/server/infra/wrappers/diarization_wrapper.py
sensory_transcription/server/infra/wrappers/emo_wrapper.py
sensory_transcription/server/infra/wrappers/whisper_wrapper.py
sensory_transcription/server/libs/gigaam/__init__.py
sensory_transcription/server/libs/gigaam/decoder.py
sensory_transcription/server/libs/gigaam/decoding.py
sensory_transcription/server/libs/gigaam/encoder.py
sensory_transcription/server/libs/gigaam/model.py
sensory_transcription/server/libs/gigaam/onnx_utils.py
sensory_transcription/server/libs/gigaam/preprocess.py
sensory_transcription/server/libs/gigaam/setup.py
sensory_transcription-0.1.0.7.dist-info/METADATA
sensory_transcription-0.1.0.7.dist-info/WHEEL
sensory_transcription-0.1.0.7.dist-info/entry_points.txt
sensory_transcription-0.1.0.7.dist-info/top_level.txt
sensory_transcription-0.1.0.7.dist-info/RECORD
