Metadata-Version: 2.4
Name: sensory-transcription
Version: 0.1.0.7
Summary: Audio transcription + diarization + emotion analysis service
Author-email: Fox <sensory@sensory.com>
License: MIT
Keywords: transcription,diarization,emotion-analysis,fastapi,ai,speech-to-text
Classifier: Programming Language :: Python :: 3
Classifier: License :: OSI Approved :: MIT License
Classifier: Operating System :: OS Independent
Classifier: Intended Audience :: Developers
Classifier: Topic :: Scientific/Engineering :: Artificial Intelligence
Classifier: Topic :: Multimedia :: Sound/Audio :: Speech
Requires-Python: >=3.9
Requires-Dist: pydantic>=2.6
Requires-Dist: pydantic-settings>=2.2
Requires-Dist: numpy
Requires-Dist: typer[all]
Requires-Dist: rich
Requires-Dist: httpx
Requires-Dist: requests
Requires-Dist: websockets
Requires-Dist: soundfile
Requires-Dist: librosa==0.10.2
Requires-Dist: python-dotenv
Provides-Extra: server
Requires-Dist: fastapi; extra == "server"
Requires-Dist: uvicorn[standard]; extra == "server"
Requires-Dist: gunicorn; extra == "server"
Requires-Dist: python-multipart; extra == "server"
Requires-Dist: prometheus-fastapi-instrumentator; extra == "server"
Requires-Dist: faster-whisper==1.1.1; extra == "server"
Requires-Dist: pyannote.audio; extra == "server"
Requires-Dist: huggingface_hub; extra == "server"
Requires-Dist: hydra-core; extra == "server"
Requires-Dist: omegaconf; extra == "server"
Requires-Dist: sentencepiece; extra == "server"
Requires-Dist: onnx; extra == "server"
Requires-Dist: onnxruntime; extra == "server"
Requires-Dist: psutil; extra == "server"
Requires-Dist: pydub; extra == "server"
Requires-Dist: noisereduce; extra == "server"
Requires-Dist: requests-toolbelt; extra == "server"
Requires-Dist: torch; extra == "server"
Requires-Dist: pandas; extra == "server"
Provides-Extra: client
Requires-Dist: tqdm; extra == "client"
Requires-Dist: tqdm-asyncio; extra == "client"
Provides-Extra: dev
Requires-Dist: pytest; extra == "dev"
Requires-Dist: pytest-asyncio; extra == "dev"
Requires-Dist: mypy; extra == "dev"
Requires-Dist: ruff; extra == "dev"
Requires-Dist: black; extra == "dev"
Requires-Dist: isort; extra == "dev"
